{
  "products": [
    {
      "id": 123,
      "name": "orange",
      "price": "2",
      "image": "https://cdn.pixabay.com/photo/2017/01/20/15/06/oranges-1995056_960_720.jpg"
    },
    {
      "id": 131,
      "name": "Milk",
      "price": "3",
      "image": "https://cdn.pixabay.com/photo/2019/03/26/12/55/milk-4082580_960_720.jpg"
    },
    {
      "id": 143,
      "name": "Ice Cream",
      "price": "6",
      "image": "https://cdn.pixabay.com/photo/2016/03/23/15/00/ice-cream-1274894_960_720.jpg"
    },
    {
      "id": 134,
      "name": "Salmon",
      "price": "10",
      "image": "https://cdn.pixabay.com/photo/2015/04/08/13/13/food-712665_960_720.jpg"
    },
    {
      "id": 131,
      "name": "Water Melon",
      "price": "13",
      "image": "https://cdn.pixabay.com/photo/2014/08/05/10/31/watermelon-410329_960_720.jpg"
    },
    {
      "id": 151,
      "name": "Potatoe",
      "price": "25",
      "image": "https://cdn.pixabay.com/photo/2014/11/04/14/15/noodles-516635_960_720.jpg"
    }
  ]
}